README.md
pyproject.toml
setup.cfg
src/ofcli/VERSION
src/ofcli/__init__.py
src/ofcli/__main__.py
src/ofcli/_version.py
src/ofcli/cli.py
src/ofcli/core.py
src/ofcli/exceptions.py
src/ofcli/fedtree.py
src/ofcli/logging.py
src/ofcli/message.py
src/ofcli/policy.py
src/ofcli/trustchain.py
src/ofcli/utils.py
src/ofcli.egg-info/PKG-INFO
src/ofcli.egg-info/SOURCES.txt
src/ofcli.egg-info/dependency_links.txt
src/ofcli.egg-info/entry_points.txt
src/ofcli.egg-info/requires.txt
src/ofcli.egg-info/top_level.txt
src/ofcli/api/__init__.py
src/ofcli/api/config.py
src/ofcli/api/api_v1/__init__.py
src/ofcli/api/api_v1/api.py
src/ofcli/api/api_v1/endpoints.py
tests/test_api.py
tests/test_core.py
tests/test_fedtree.py
tests/test_trustchains.py
tests/test_utils.py