Metadata-Version: 2.4
Name: ofcli
Version: 0.6.9
Summary: helper CLI tool for OIDC federation exploration
Home-page: https://gitlab.geant.org/TI_Incubator/oidcfed/ofcli
Author: Diana Gudu
Author-email: gudu@kit.edu
License: MIT
Project-URL: Bug Tracker, https://gitlab.geant.org/TI_Incubator/oidcfed/ofcli/issues
Classifier: Development Status :: 3 - Alpha
Classifier: Environment :: Console
Classifier: Environment :: Web Environment
Classifier: Intended Audience :: Developers
Classifier: Intended Audience :: Information Technology
Classifier: Intended Audience :: Science/Research
Classifier: Intended Audience :: System Administrators
Classifier: License :: OSI Approved :: MIT License
Classifier: Operating System :: OS Independent
Classifier: Natural Language :: English
Classifier: Programming Language :: Python
Classifier: Programming Language :: Python :: 3
Classifier: Programming Language :: Python :: 3.8
Classifier: Programming Language :: Python :: 3.9
Classifier: Programming Language :: Python :: 3.10
Classifier: Programming Language :: Python :: 3.11
Classifier: Topic :: System :: Systems Administration
Classifier: Topic :: System :: Systems Administration :: Authentication/Directory
Classifier: Topic :: Utilities
Requires-Dist: click
Requires-Dist: click_logging
Requires-Dist: requests
Requires-Dist: cryptojwt
Requires-Dist: pygraphviz
Requires-Dist: fastapi
Requires-Dist: uvicorn[standard]
Requires-Dist: oidcmsg
Requires-Dist: pydantic_settings
Requires-Dist: typing_extensions
Requires-Dist: aiohttp[speedups]
